[
  {
    "conditions": [
      {
        "type": "aether:seeEntity",
        "entityId": "aether:glitterwing"
      }
    ],
    "resolution": "requireAll",
    "entries": {
      "aether.glitterwing.discovery": {
        "tag": "bestiary",
        "type": "bestiary_page",
        "entityId": "aether:glitterwing",
        "silhouetteTexture": "aether:textures/discoveries/bestiary/placeholder/silhouette.png",
        "discoveredTexture": "aether:textures/discoveries/bestiary/placeholder/discovered.png",
        "silhouetteSlotTexture": "aether:textures/discoveries/bestiary/placeholder/silhouette_slot.png",
        "discoveredSlotTexture": "aether:textures/discoveries/bestiary/placeholder/discovered_slot.png",
        "description": "aether.placeholder.discovery.description"
      }
    }
  }
]